{
  "project_info": {
    "project_number": "116759431954",
    "project_id": "mydatabase-794b9",
    "storage_bucket": "mydatabase-794b9.appspot.com"
  },
  "client": [
    {
      "client_info": {
        "mobilesdk_app_id": "1:116759431954:android:b85f07fb4785f4bcbfc1cb",
        "android_client_info": {
          "package_name": "com.betelgeuse.firebasecloud"
        }
      },
      "oauth_client": [
        {
          "client_id": "116759431954-dhppnqm6vuuakdavj38vovmg0spqm1ot.apps.googleusercontent.com",
          "client_type": 3
        }
      ],
      "api_key": [
        {
          "current_key": "AIzaSyBLa5SvpFeiHIlZtxKMfho7V69kwI_OdOA"
        }
      ],
      "services": {
        "appinvite_service": {
          "other_platform_oauth_client": [
            {
              "client_id": "116759431954-dhppnqm6vuuakdavj38vovmg0spqm1ot.apps.googleusercontent.com",
              "client_type": 3
            }
          ]
        }
      }
    },
    {
      "client_info": {
        "mobilesdk_app_id": "1:116759431954:android:47cbd7223599dd09bfc1cb",
        "android_client_info": {
          "package_name": "com.betelgeuse.firebasecloud2"
        }
      },
      "oauth_client": [
        {
          "client_id": "116759431954-dhppnqm6vuuakdavj38vovmg0spqm1ot.apps.googleusercontent.com",
          "client_type": 3
        }
      ],
      "api_key": [
        {
          "current_key": "AIzaSyBLa5SvpFeiHIlZtxKMfho7V69kwI_OdOA"
        }
      ],
      "services": {
        "appinvite_service": {
          "other_platform_oauth_client": [
            {
              "client_id": "116759431954-dhppnqm6vuuakdavj38vovmg0spqm1ot.apps.googleusercontent.com",
              "client_type": 3
            }
          ]
        }
      }
    }
  ],
  "configuration_version": "1"
}